<news>
  <entry>
    <date>2025-09-02T00:00:00</date>
    <title>Watch on Twitch</title>
    <text>Live streams, VODs, and chat.</text>
    <link>https://www.twitch.tv/mcbeth_gaming</link>
  </entry>
  <entry>
    <date>2025-09-02T00:00:00</date>
    <title>TikTok</title>
    <text>Clips, lives, and community highlights.</text>
    <link>https://www.tiktok.com/@mcbeth_gaming</link>
  </entry>
  <entry>
    <date>2025-09-02T00:00:00</date>
    <title>All Links (Linktree)</title>
    <text>One hub for everything McBeth Gaming.</text>
    <link>https://linktr.ee/McBethGaming</link>
  </entry>
</news>
